{
  "entities": [
    {
      "id": 1764380333288,
      "type": "green_sensor",
      "x": 1,
      "y": 6.7,
      "width": 1.2000000000000002,
      "height": 12.4,
      "direction": 0
    },
    {
      "id": 1764380349114,
      "type": "barrier",
      "x": 3.2,
      "y": 0.5,
      "width": 2.6,
      "height": 10.700000000000001,
      "direction": 0
    },
    {
      "id": 1764380375946,
      "type": "occluder",
      "x": 5.800000000000001,
      "y": 2.5,
      "width": 10,
      "height": 16.1,
      "direction": 0
    },
    {
      "id": 1764380415306,
      "type": "red_sensor",
      "x": 19,
      "y": 4.7,
      "width": 0.9,
      "height": 14.8,
      "direction": 0
    },
    {
      "id": 1764380432745,
      "type": "barrier",
      "x": 1.4000000000000004,
      "y": 4.2,
      "width": 1.8,
      "height": 1,
      "direction": 0
    },
    {
      "id": 1764380443470,
      "type": "target",
      "x": 17.474079705853647,
      "y": 0.7372855200172843,
      "width": 1,
      "height": 1,
      "direction": -0.6614797865058508
    },
    {
      "id": 1772172821867,
      "type": "barrier",
      "x": 6.300000000000001,
      "y": 0.9,
      "width": 5.800000000000001,
      "height": 1,
      "direction": 0
    }
  ],
  "simulationParams": {
    "videoLength": 12,
    "ballSpeed": 3.6,
    "fps": 30,
    "worldWidth": 20,
    "worldHeight": 20
  }
}