{
  "barriers": [
    {
      "x": 1.8,
      "y": 45.9,
      "width": 13.9,
      "height": 16.0
    },
    {
      "x": 89.6,
      "y": 9.5,
      "width": 10.3,
      "height": 16.3
    },
    {
      "x": 49.3,
      "y": 14.4,
      "width": 8.6,
      "height": 5.2
    },
    {
      "x": 65.0,
      "y": 29.6,
      "width": 26.0,
      "height": 10.9
    }
  ],
  "occluders": [],
  "step_data": {
    "0": {
      "x": 79.55,
      "y": 40.7,
      "speed": 1.0,
      "dir": 0.0,
      "vx": 0.0,
      "vy": 0.0
    },
    "1": {
      "x": 80.95,
      "y": 40.65,
      "speed": 1.0,
      "dir": -0.03569911267932687,
      "vx": 0.9993628543475495,
      "vy": -0.03569153051241538
    },
    "2": {
      "x": 82.4,
      "y": 40.9,
      "speed": 1.0,
      "dir": 0.17073521147528248,
      "vx": 0.985460115744348,
      "vy": 0.1699069165076459
    },
    "3": {
      "x": 84.0,
      "y": 41.1,
      "speed": 1.0,
      "dir": 0.12435499454676363,
      "vx": 0.9922778767136673,
      "vy": 0.12403473458921063
    },
    "4": {
      "x": 85.5,
      "y": 41.3,
      "speed": 1.0,
      "dir": 0.13255153229667124,
      "vx": 0.991227900682635,
      "vy": 0.13216372009101518
    },
    "5": {
      "x": 87.0,
      "y": 41.4,
      "speed": 1.0,
      "dir": 0.06656816377582475,
      "vx": 0.9977851578566089,
      "vy": 0.06651901052377487
    },
    "6": {
      "x": 88.45,
      "y": 41.65,
      "speed": 1.0,
      "dir": 0.17073521147528248,
      "vx": 0.985460115744348,
      "vy": 0.1699069165076459
    },
    "7": {
      "x": 89.85,
      "y": 41.85,
      "speed": 1.0,
      "dir": 0.14189705460416677,
      "vx": 0.9899494936611661,
      "vy": 0.1414213562373123
    },
    "8": {
      "x": 91.3,
      "y": 42.1,
      "speed": 1.0,
      "dir": 0.17073521147528248,
      "vx": 0.985460115744348,
      "vy": 0.1699069165076459
    },
    "9": {
      "x": 92.8,
      "y": 42.2,
      "speed": 1.0,
      "dir": 0.06656816377582475,
      "vx": 0.9977851578566089,
      "vy": 0.06651901052377487
    },
    "10": {
      "x": 94.3,
      "y": 42.5,
      "speed": 1.0,
      "dir": 0.19739555984987894,
      "vx": 0.9805806756909206,
      "vy": 0.19611613513818227
    },
    "11": {
      "x": 95.85,
      "y": 42.75,
      "speed": 1.0,
      "dir": 0.15991312315821957,
      "vx": 0.9872411207126471,
      "vy": 0.1592324388246208
    },
    "12": {
      "x": 94.55,
      "y": 42.95,
      "speed": 1.0,
      "dir": 2.9889433251945254,
      "vx": -0.9883716976506168,
      "vy": 0.15205718425394354
    },
    "13": {
      "x": 93.05,
      "y": 43.15,
      "speed": 1.0,
      "dir": 3.009041121293122,
      "vx": -0.991227900682635,
      "vy": 0.13216372009101518
    },
    "14": {
      "x": 91.55,
      "y": 43.35,
      "speed": 1.0,
      "dir": 3.009041121293117,
      "vx": -0.9912279006826344,
      "vy": 0.13216372009101982
    },
    "15": {
      "x": 90.05,
      "y": 43.55,
      "speed": 1.0,
      "dir": 3.009041121293122,
      "vx": -0.991227900682635,
      "vy": 0.13216372009101518
    },
    "16": {
      "x": 88.5,
      "y": 43.7,
      "speed": 1.0,
      "dir": 3.0451188784072025,
      "vx": -0.9953500135552997,
      "vy": 0.09632419486019414
    },
    "17": {
      "x": 87.15,
      "y": 43.95,
      "speed": 1.0,
      "dir": 2.958481836327308,
      "vx": -0.98328200498446,
      "vy": 0.18208926018230817
    },
    "18": {
      "x": 85.7,
      "y": 44.2,
      "speed": 1.0,
      "dir": 2.970857442114511,
      "vx": -0.985460115744348,
      "vy": 0.1699069165076459
    },
    "19": {
      "x": 84.1,
      "y": 44.3,
      "speed": 1.0,
      "dir": 3.0791738435938396,
      "vx": -0.9980525784828889,
      "vy": 0.062378286155176675
    },
    "20": {
      "x": 82.65,
      "y": 44.55,
      "speed": 1.0,
      "dir": 2.970857442114509,
      "vx": -0.9854601157443478,
      "vy": 0.1699069165076475
    },
    "21": {
      "x": 81.15,
      "y": 44.85,
      "speed": 1.0,
      "dir": 2.9441970937399096,
      "vx": -0.9805806756909196,
      "vy": 0.1961161351381867
    },
    "22": {
      "x": 79.65,
      "y": 45.05,
      "speed": 1.0,
      "dir": 3.009041121293122,
      "vx": -0.991227900682635,
      "vy": 0.13216372009101518
    },
    "23": {
      "x": 78.15,
      "y": 45.25,
      "speed": 1.0,
      "dir": 3.009041121293117,
      "vx": -0.9912279006826344,
      "vy": 0.13216372009101982
    },
    "24": {
      "x": 76.75,
      "y": 45.45,
      "speed": 1.0,
      "dir": 2.9996955989856278,
      "vx": -0.9899494936611664,
      "vy": 0.14142135623731092
    },
    "25": {
      "x": 75.2,
      "y": 45.7,
      "speed": 1.0,
      "dir": 2.9816795304315735,
      "vx": -0.9872411207126471,
      "vy": 0.1592324388246208
    },
    "26": {
      "x": 73.7,
      "y": 45.85,
      "speed": 1.0,
      "dir": 3.041924001098632,
      "vx": -0.9950371902099892,
      "vy": 0.09950371902099799
    },
    "27": {
      "x": 72.2,
      "y": 46.1,
      "speed": 1.0,
      "dir": 2.976443976175166,
      "vx": -0.9863939238321437,
      "vy": 0.1643989873053573
    },
    "28": {
      "x": 70.75,
      "y": 46.25,
      "speed": 1.0,
      "dir": 3.0385110450670942,
      "vx": -0.9946917938265513,
      "vy": 0.10289915108550414
    },
    "29": {
      "x": 69.3,
      "y": 46.45,
      "speed": 1.0,
      "dir": 3.004526479279604,
      "vx": -0.9906211292434747,
      "vy": 0.13663739713703266
    },
    "30": {
      "x": 67.75,
      "y": 46.75,
      "speed": 1.0,
      "dir": 2.9504081939927804,
      "vx": -0.9817798505902816,
      "vy": 0.19002190656585952
    },
    "31": {
      "x": 66.35,
      "y": 46.95,
      "speed": 1.0,
      "dir": 2.9996955989856278,
      "vx": -0.9899494936611664,
      "vy": 0.14142135623731092
    },
    "32": {
      "x": 64.9,
      "y": 47.15,
      "speed": 1.0,
      "dir": 3.0045264792796074,
      "vx": -0.9906211292434751,
      "vy": 0.13663739713702922
    },
    "33": {
      "x": 63.3,
      "y": 47.3,
      "speed": 1.0,
      "dir": 3.048115872431205,
      "vx": -0.9956342260592882,
      "vy": 0.0933407086930569
    },
    "34": {
      "x": 61.85,
      "y": 47.55,
      "speed": 1.0,
      "dir": 2.97085744211451,
      "vx": -0.985460115744348,
      "vy": 0.1699069165076467
    },
    "35": {
      "x": 60.35,
      "y": 47.75,
      "speed": 1.0,
      "dir": 3.009041121293117,
      "vx": -0.9912279006826344,
      "vy": 0.13216372009101982
    },
    "36": {
      "x": 58.85,
      "y": 47.95,
      "speed": 1.0,
      "dir": 3.009041121293117,
      "vx": -0.9912279006826344,
      "vy": 0.13216372009101982
    },
    "37": {
      "x": 57.45,
      "y": 48.15,
      "speed": 1.0,
      "dir": 2.999695598985632,
      "vx": -0.9899494936611669,
      "vy": 0.14142135623730667
    },
    "38": {
      "x": 55.95,
      "y": 48.35,
      "speed": 1.0,
      "dir": 3.009041121293117,
      "vx": -0.9912279006826344,
      "vy": 0.13216372009101982
    },
    "39": {
      "x": 54.4,
      "y": 48.6,
      "speed": 1.0,
      "dir": 2.9816795304315744,
      "vx": -0.9872411207126471,
      "vy": 0.15923243882462007
    },
    "40": {
      "x": 52.9,
      "y": 48.9,
      "speed": 1.0,
      "dir": 2.9441970937399145,
      "vx": -0.9805806756909206,
      "vy": 0.19611613513818227
    },
    "41": {
      "x": 51.4,
      "y": 49.0,
      "speed": 1.0,
      "dir": 3.0750244898139685,
      "vx": -0.9977851578566089,
      "vy": 0.06651901052377487
    },
    "42": {
      "x": 49.95,
      "y": 49.25,
      "speed": 1.0,
      "dir": 2.97085744211451,
      "vx": -0.985460115744348,
      "vy": 0.1699069165076467
    },
    "43": {
      "x": 48.5,
      "y": 49.4,
      "speed": 1.0,
      "dir": 3.0385110450670942,
      "vx": -0.9946917938265513,
      "vy": 0.10289915108550414
    },
    "44": {
      "x": 47.1,
      "y": 49.6,
      "speed": 1.0,
      "dir": 2.9996955989856273,
      "vx": -0.9899494936611661,
      "vy": 0.1414213562373116
    },
    "45": {
      "x": 45.55,
      "y": 49.85,
      "speed": 1.0,
      "dir": 2.9816795304315744,
      "vx": -0.9872411207126471,
      "vy": 0.15923243882462007
    },
    "46": {
      "x": 44.05,
      "y": 50.05,
      "speed": 1.0,
      "dir": 3.009041121293122,
      "vx": -0.991227900682635,
      "vy": 0.13216372009101518
    },
    "47": {
      "x": 42.55,
      "y": 50.25,
      "speed": 1.0,
      "dir": 3.009041121293117,
      "vx": -0.9912279006826344,
      "vy": 0.13216372009101982
    },
    "48": {
      "x": 41.05,
      "y": 50.45,
      "speed": 1.0,
      "dir": 3.009041121293117,
      "vx": -0.9912279006826344,
      "vy": 0.13216372009101982
    },
    "49": {
      "x": 39.6,
      "y": 50.7,
      "speed": 1.0,
      "dir": 2.97085744211451,
      "vx": -0.985460115744348,
      "vy": 0.1699069165076467
    },
    "50": {
      "x": 38.05,
      "y": 50.95,
      "speed": 1.0,
      "dir": 2.9816795304315744,
      "vx": -0.9872411207126471,
      "vy": 0.15923243882462007
    },
    "51": {
      "x": 36.65,
      "y": 51.15,
      "speed": 1.0,
      "dir": 2.999695598985632,
      "vx": -0.9899494936611669,
      "vy": 0.14142135623730667
    },
    "52": {
      "x": 35.2,
      "y": 51.4,
      "speed": 1.0,
      "dir": 2.97085744211451,
      "vx": -0.985460115744348,
      "vy": 0.1699069165076467
    },
    "53": {
      "x": 33.6,
      "y": 51.5,
      "speed": 1.0,
      "dir": 3.079173843593835,
      "vx": -0.9980525784828885,
      "vy": 0.062378286155181366
    },
    "54": {
      "x": 32.2,
      "y": 51.7,
      "speed": 1.0,
      "dir": 2.9996955989856273,
      "vx": -0.9899494936611661,
      "vy": 0.1414213562373116
    },
    "55": {
      "x": 30.700000000000003,
      "y": 52.0,
      "speed": 1.0,
      "dir": 2.9441970937399145,
      "vx": -0.9805806756909206,
      "vy": 0.19611613513818227
    },
    "56": {
      "x": 29.15,
      "y": 52.15,
      "speed": 1.0,
      "dir": 3.0451188784072074,
      "vx": -0.9953500135553002,
      "vy": 0.09632419486018916
    },
    "57": {
      "x": 27.65,
      "y": 52.35,
      "speed": 1.0,
      "dir": 3.009041121293117,
      "vx": -0.9912279006826344,
      "vy": 0.13216372009101982
    },
    "58": {
      "x": 26.25,
      "y": 52.55,
      "speed": 1.0,
      "dir": 2.999695598985632,
      "vx": -0.9899494936611669,
      "vy": 0.14142135623730667
    },
    "59": {
      "x": 24.75,
      "y": 52.75,
      "speed": 1.0,
      "dir": 3.009041121293117,
      "vx": -0.9912279006826344,
      "vy": 0.13216372009101982
    },
    "60": {
      "x": 23.25,
      "y": 53.05,
      "speed": 1.0,
      "dir": 2.9441970937399145,
      "vx": -0.9805806756909206,
      "vy": 0.19611613513818227
    },
    "61": {
      "x": 21.75,
      "y": 53.25,
      "speed": 1.0,
      "dir": 3.009041121293117,
      "vx": -0.9912279006826344,
      "vy": 0.13216372009101982
    },
    "62": {
      "x": 20.3,
      "y": 53.4,
      "speed": 1.0,
      "dir": 3.038511045067094,
      "vx": -0.9946917938265513,
      "vy": 0.10289915108550438
    },
    "63": {
      "x": 18.75,
      "y": 53.65,
      "speed": 1.0,
      "dir": 2.981679530431574,
      "vx": -0.9872411207126471,
      "vy": 0.15923243882462043
    },
    "64": {
      "x": 17.25,
      "y": 53.85,
      "speed": 1.0,
      "dir": 3.009041121293117,
      "vx": -0.9912279006826344,
      "vy": 0.13216372009101982
    },
    "65": {
      "x": 15.850000000000001,
      "y": 54.05,
      "speed": 1.0,
      "dir": 2.999695598985632,
      "vx": -0.9899494936611669,
      "vy": 0.14142135623730667
    },
    "66": {
      "x": 16.9,
      "y": 54.2,
      "speed": 1.0,
      "dir": 0.14189705460416963,
      "vx": 0.9899494936611657,
      "vy": 0.14142135623731514
    },
    "67": {
      "x": 18.35,
      "y": 54.45,
      "speed": 1.0,
      "dir": 0.17073521147528248,
      "vx": 0.985460115744348,
      "vy": 0.1699069165076459
    },
    "68": {
      "x": 19.75,
      "y": 54.65,
      "speed": 1.0,
      "dir": 0.14189705460416108,
      "vx": 0.9899494936611669,
      "vy": 0.14142135623730667
    },
    "69": {
      "x": 21.3,
      "y": 54.9,
      "speed": 1.0,
      "dir": 0.1599131231582192,
      "vx": 0.9872411207126471,
      "vy": 0.15923243882462043
    },
    "70": {
      "x": 22.75,
      "y": 55.15,
      "speed": 1.0,
      "dir": 0.1707352114752829,
      "vx": 0.985460115744348,
      "vy": 0.16990691650764628
    },
    "71": {
      "x": 24.3,
      "y": 55.3,
      "speed": 1.0,
      "dir": 0.09647377518258596,
      "vx": 0.9953500135553002,
      "vy": 0.09632419486018938
    },
    "72": {
      "x": 25.75,
      "y": 55.55,
      "speed": 1.0,
      "dir": 0.1707352114752829,
      "vx": 0.985460115744348,
      "vy": 0.16990691650764628
    },
    "73": {
      "x": 27.2,
      "y": 55.8,
      "speed": 1.0,
      "dir": 0.1707352114752829,
      "vx": 0.985460115744348,
      "vy": 0.16990691650764628
    },
    "74": {
      "x": 28.75,
      "y": 55.95,
      "speed": 1.0,
      "dir": 0.09647377518259051,
      "vx": 0.9953500135552997,
      "vy": 0.09632419486019392
    },
    "75": {
      "x": 30.15,
      "y": 56.15,
      "speed": 1.0,
      "dir": 0.14189705460416108,
      "vx": 0.9899494936611669,
      "vy": 0.14142135623730667
    },
    "76": {
      "x": 31.65,
      "y": 56.35,
      "speed": 1.0,
      "dir": 0.1325515322966759,
      "vx": 0.9912279006826344,
      "vy": 0.13216372009101982
    },
    "77": {
      "x": 33.2,
      "y": 56.6,
      "speed": 1.0,
      "dir": 0.15991312315821885,
      "vx": 0.9872411207126471,
      "vy": 0.15923243882462007
    },
    "78": {
      "x": 34.7,
      "y": 56.8,
      "speed": 1.0,
      "dir": 0.13255153229667124,
      "vx": 0.991227900682635,
      "vy": 0.13216372009101518
    },
    "79": {
      "x": 36.1,
      "y": 57.0,
      "speed": 1.0,
      "dir": 0.14189705460416607,
      "vx": 0.9899494936611661,
      "vy": 0.1414213562373116
    },
    "80": {
      "x": 37.7,
      "y": 57.3,
      "speed": 1.0,
      "dir": 0.18534794999569287,
      "vx": 0.9828721869343222,
      "vy": 0.1842885350501835
    },
    "81": {
      "x": 39.1,
      "y": 57.4,
      "speed": 1.0,
      "dir": 0.07130746478529142,
      "vx": 0.9974586998307349,
      "vy": 0.07124704998791072
    },
    "82": {
      "x": 40.55,
      "y": 57.65,
      "speed": 1.0,
      "dir": 0.1707352114752833,
      "vx": 0.985460115744348,
      "vy": 0.1699069165076467
    },
    "83": {
      "x": 42.1,
      "y": 57.9,
      "speed": 1.0,
      "dir": 0.15991312315821885,
      "vx": 0.9872411207126471,
      "vy": 0.15923243882462007
    },
    "84": {
      "x": 43.55,
      "y": 58.05,
      "speed": 1.0,
      "dir": 0.10308160852269957,
      "vx": 0.9946917938265513,
      "vy": 0.10289915108550463
    },
    "85": {
      "x": 45.05,
      "y": 57.95,
      "speed": 1.0,
      "dir": -0.06656816377582003,
      "vx": 0.9977851578566092,
      "vy": -0.06651901052377017
    },
    "86": {
      "x": 46.6,
      "y": 57.8,
      "speed": 1.0,
      "dir": -0.09647377518259027,
      "vx": 0.9953500135552998,
      "vy": -0.0963241948601937
    },
    "87": {
      "x": 48.0,
      "y": 57.6,
      "speed": 1.0,
      "dir": -0.14189705460416108,
      "vx": 0.9899494936611669,
      "vy": -0.14142135623730667
    },
    "88": {
      "x": 49.45,
      "y": 57.35,
      "speed": 1.0,
      "dir": -0.17073521147528248,
      "vx": 0.985460115744348,
      "vy": -0.1699069165076459
    },
    "89": {
      "x": 51.0,
      "y": 57.1,
      "speed": 1.0,
      "dir": -0.15991312315821957,
      "vx": 0.9872411207126471,
      "vy": -0.1592324388246208
    },
    "90": {
      "x": 52.5,
      "y": 56.85,
      "speed": 1.0,
      "dir": -0.16514867741462685,
      "vx": 0.9863939238321437,
      "vy": -0.1643989873053573
    },
    "91": {
      "x": 53.9,
      "y": 56.6,
      "speed": 1.0,
      "dir": -0.1767088560700368,
      "vx": 0.9844275755084819,
      "vy": -0.17579063848365767
    },
    "92": {
      "x": 55.45,
      "y": 56.45,
      "speed": 1.0,
      "dir": -0.09647377518258574,
      "vx": 0.9953500135553002,
      "vy": -0.09632419486018916
    },
    "93": {
      "x": 56.95,
      "y": 56.25,
      "speed": 1.0,
      "dir": -0.1325515322966759,
      "vx": 0.9912279006826344,
      "vy": -0.13216372009101982
    },
    "94": {
      "x": 58.5,
      "y": 56.1,
      "speed": 1.0,
      "dir": -0.09647377518258618,
      "vx": 0.9953500135553002,
      "vy": -0.09632419486018962
    },
    "95": {
      "x": 59.85,
      "y": 55.85,
      "speed": 1.0,
      "dir": -0.18311081726248393,
      "vx": 0.9832820049844603,
      "vy": -0.18208926018230726
    },
    "96": {
      "x": 61.35,
      "y": 55.65,
      "speed": 1.0,
      "dir": -0.1325515322966759,
      "vx": 0.9912279006826344,
      "vy": -0.13216372009101982
    },
    "97": {
      "x": 62.900000000000006,
      "y": 55.4,
      "speed": 1.0,
      "dir": -0.15991312315821885,
      "vx": 0.9872411207126471,
      "vy": -0.15923243882462007
    },
    "98": {
      "x": 64.35,
      "y": 55.25,
      "speed": 1.0,
      "dir": -0.10308160852270006,
      "vx": 0.9946917938265513,
      "vy": -0.10289915108550513
    },
    "99": {
      "x": 65.8,
      "y": 55.1,
      "speed": 1.0,
      "dir": -0.10308160852269907,
      "vx": 0.9946917938265513,
      "vy": -0.10289915108550414
    },
    "100": {
      "x": 67.35,
      "y": 54.75,
      "speed": 1.0,
      "dir": -0.22208190190548144,
      "vx": 0.9754410020677062,
      "vy": -0.22026087143464465
    },
    "101": {
      "x": 68.85,
      "y": 54.55,
      "speed": 1.0,
      "dir": -0.1325515322966759,
      "vx": 0.9912279006826344,
      "vy": -0.13216372009101982
    },
    "102": {
      "x": 70.25,
      "y": 54.35,
      "speed": 1.0,
      "dir": -0.14189705460416038,
      "vx": 0.9899494936611671,
      "vy": -0.141421356237306
    },
    "103": {
      "x": 71.8,
      "y": 54.1,
      "speed": 1.0,
      "dir": -0.15991312315821957,
      "vx": 0.9872411207126471,
      "vy": -0.1592324388246208
    },
    "104": {
      "x": 73.25,
      "y": 53.95,
      "speed": 1.0,
      "dir": -0.10308160852269907,
      "vx": 0.9946917938265513,
      "vy": -0.10289915108550414
    },
    "105": {
      "x": 74.75,
      "y": 53.75,
      "speed": 1.0,
      "dir": -0.1325515322966759,
      "vx": 0.9912279006826344,
      "vy": -0.13216372009101982
    },
    "106": {
      "x": 76.25,
      "y": 53.55,
      "speed": 1.0,
      "dir": -0.1325515322966759,
      "vx": 0.9912279006826344,
      "vy": -0.13216372009101982
    },
    "107": {
      "x": 77.75,
      "y": 53.35,
      "speed": 1.0,
      "dir": -0.13255153229667124,
      "vx": 0.991227900682635,
      "vy": -0.13216372009101518
    },
    "108": {
      "x": 79.25,
      "y": 53.15,
      "speed": 1.0,
      "dir": -0.1325515322966759,
      "vx": 0.9912279006826344,
      "vy": -0.13216372009101982
    },
    "109": {
      "x": 80.65,
      "y": 52.95,
      "speed": 1.0,
      "dir": -0.14189705460416038,
      "vx": 0.9899494936611671,
      "vy": -0.141421356237306
    },
    "110": {
      "x": 82.2,
      "y": 52.6,
      "speed": 1.0,
      "dir": -0.22208190190548144,
      "vx": 0.9754410020677062,
      "vy": -0.22026087143464465
    },
    "111": {
      "x": 83.7,
      "y": 52.4,
      "speed": 1.0,
      "dir": -0.1325515322966759,
      "vx": 0.9912279006826344,
      "vy": -0.13216372009101982
    },
    "112": {
      "x": 85.15,
      "y": 52.25,
      "speed": 1.0,
      "dir": -0.10308160852269907,
      "vx": 0.9946917938265513,
      "vy": -0.10289915108550414
    },
    "113": {
      "x": 86.6,
      "y": 52.0,
      "speed": 1.0,
      "dir": -0.17073521147528412,
      "vx": 0.9854601157443478,
      "vy": -0.1699069165076475
    },
    "114": {
      "x": 88.1,
      "y": 51.9,
      "speed": 1.0,
      "dir": -0.06656816377582475,
      "vx": 0.9977851578566089,
      "vy": -0.06651901052377487
    },
    "115": {
      "x": 89.55,
      "y": 51.65,
      "speed": 1.0,
      "dir": -0.17073521147528248,
      "vx": 0.985460115744348,
      "vy": -0.1699069165076459
    },
    "116": {
      "x": 91.05,
      "y": 51.45,
      "speed": 1.0,
      "dir": -0.13255153229667124,
      "vx": 0.991227900682635,
      "vy": -0.13216372009101518
    },
    "117": {
      "x": 92.55,
      "y": 51.25,
      "speed": 1.0,
      "dir": -0.1325515322966759,
      "vx": 0.9912279006826344,
      "vy": -0.13216372009101982
    },
    "118": {
      "x": 94.05,
      "y": 51.05,
      "speed": 1.0,
      "dir": -0.1325515322966759,
      "vx": 0.9912279006826344,
      "vy": -0.13216372009101982
    },
    "119": {
      "x": 95.55,
      "y": 50.85,
      "speed": 1.0,
      "dir": -0.13255153229667124,
      "vx": 0.991227900682635,
      "vy": -0.13216372009101518
    },
    "120": {
      "x": 94.85,
      "y": 50.55,
      "speed": 1.0,
      "dir": -2.736700867304706,
      "vx": -0.9191450300180565,
      "vy": -0.3939192985791711
    },
    "121": {
      "x": 93.35,
      "y": 50.35,
      "speed": 1.0,
      "dir": -3.009041121293122,
      "vx": -0.991227900682635,
      "vy": -0.13216372009101518
    },
    "122": {
      "x": 91.9,
      "y": 50.15,
      "speed": 1.0,
      "dir": -3.0045264792796025,
      "vx": -0.9906211292434745,
      "vy": -0.13663739713703396
    },
    "123": {
      "x": 90.4,
      "y": 49.9,
      "speed": 1.0,
      "dir": -2.976443976175166,
      "vx": -0.9863939238321437,
      "vy": -0.1643989873053573
    },
    "124": {
      "x": 88.9,
      "y": 49.8,
      "speed": 1.0,
      "dir": -3.0750244898139685,
      "vx": -0.9977851578566089,
      "vy": -0.06651901052377487
    },
    "125": {
      "x": 87.45,
      "y": 49.55,
      "speed": 1.0,
      "dir": -2.970857442114511,
      "vx": -0.985460115744348,
      "vy": -0.1699069165076459
    },
    "126": {
      "x": 85.95,
      "y": 49.35,
      "speed": 1.0,
      "dir": -3.009041121293122,
      "vx": -0.991227900682635,
      "vy": -0.13216372009101518
    },
    "127": {
      "x": 84.45,
      "y": 49.15,
      "speed": 1.0,
      "dir": -3.009041121293117,
      "vx": -0.9912279006826344,
      "vy": -0.13216372009101982
    },
    "128": {
      "x": 82.95,
      "y": 48.95,
      "speed": 1.0,
      "dir": -3.009041121293122,
      "vx": -0.991227900682635,
      "vy": -0.13216372009101518
    },
    "129": {
      "x": 81.4,
      "y": 48.7,
      "speed": 1.0,
      "dir": -2.9816795304315735,
      "vx": -0.9872411207126471,
      "vy": -0.1592324388246208
    },
    "130": {
      "x": 80.0,
      "y": 48.5,
      "speed": 1.0,
      "dir": -2.9996955989856278,
      "vx": -0.9899494936611664,
      "vy": -0.14142135623731092
    },
    "131": {
      "x": 78.4,
      "y": 48.25,
      "speed": 1.0,
      "dir": -2.9865959116658516,
      "vx": -0.9880120337511014,
      "vy": -0.15437688027361016
    },
    "132": {
      "x": 77.05,
      "y": 48.05,
      "speed": 1.0,
      "dir": -2.9945142982013895,
      "vx": -0.9892034623538706,
      "vy": -0.14654866108946346
    },
    "133": {
      "x": 75.55,
      "y": 47.85,
      "speed": 1.0,
      "dir": -3.009041121293122,
      "vx": -0.991227900682635,
      "vy": -0.13216372009101518
    },
    "134": {
      "x": 74.1,
      "y": 47.65,
      "speed": 1.0,
      "dir": -3.004526479279604,
      "vx": -0.9906211292434747,
      "vy": -0.13663739713703266
    },
    "135": {
      "x": 72.6,
      "y": 47.5,
      "speed": 1.0,
      "dir": -3.041924001098632,
      "vx": -0.9950371902099892,
      "vy": -0.09950371902099799
    },
    "136": {
      "x": 71.1,
      "y": 47.25,
      "speed": 1.0,
      "dir": -2.976443976175166,
      "vx": -0.9863939238321437,
      "vy": -0.1643989873053573
    },
    "137": {
      "x": 69.55,
      "y": 47.05,
      "speed": 1.0,
      "dir": -3.0132694259039963,
      "vx": -0.9917778666340249,
      "vy": -0.12797133763019883
    },
    "138": {
      "x": 68.05,
      "y": 46.85,
      "speed": 1.0,
      "dir": -3.009041121293122,
      "vx": -0.991227900682635,
      "vy": -0.13216372009101518
    },
    "139": {
      "x": 66.65,
      "y": 46.55,
      "speed": 1.0,
      "dir": -2.9304993203670424,
      "vx": -0.9778024140774085,
      "vy": -0.2095290887308775
    },
    "140": {
      "x": 65.15,
      "y": 46.35,
      "speed": 1.0,
      "dir": -3.009041121293122,
      "vx": -0.991227900682635,
      "vy": -0.13216372009101518
    },
    "141": {
      "x": 63.650000000000006,
      "y": 46.15,
      "speed": 1.0,
      "dir": -3.009041121293117,
      "vx": -0.9912279006826344,
      "vy": -0.13216372009101982
    },
    "142": {
      "x": 62.2,
      "y": 45.9,
      "speed": 1.0,
      "dir": -2.970857442114511,
      "vx": -0.985460115744348,
      "vy": -0.1699069165076459
    },
    "143": {
      "x": 60.6,
      "y": 45.8,
      "speed": 1.0,
      "dir": -3.079173843593835,
      "vx": -0.9980525784828885,
      "vy": -0.062378286155181366
    },
    "144": {
      "x": 59.15,
      "y": 45.55,
      "speed": 1.0,
      "dir": -2.970857442114511,
      "vx": -0.985460115744348,
      "vy": -0.1699069165076459
    },
    "145": {
      "x": 57.65,
      "y": 45.35,
      "speed": 1.0,
      "dir": -3.009041121293122,
      "vx": -0.991227900682635,
      "vy": -0.13216372009101518
    },
    "146": {
      "x": 56.25,
      "y": 45.15,
      "speed": 1.0,
      "dir": -2.9996955989856273,
      "vx": -0.9899494936611661,
      "vy": -0.1414213562373116
    },
    "147": {
      "x": 54.75,
      "y": 44.95,
      "speed": 1.0,
      "dir": -3.009041121293122,
      "vx": -0.991227900682635,
      "vy": -0.13216372009101518
    },
    "148": {
      "x": 53.25,
      "y": 44.75,
      "speed": 1.0,
      "dir": -3.009041121293117,
      "vx": -0.9912279006826344,
      "vy": -0.13216372009101982
    },
    "149": {
      "x": 51.8,
      "y": 44.45,
      "speed": 1.0,
      "dir": -2.937574673997247,
      "vx": -0.9792604195071032,
      "vy": -0.20260560403595007
    },
    "150": {
      "x": 50.3,
      "y": 44.25,
      "speed": 1.0,
      "dir": -3.009041121293117,
      "vx": -0.9912279006826344,
      "vy": -0.13216372009101982
    },
    "151": {
      "x": 48.75,
      "y": 44.05,
      "speed": 1.0,
      "dir": -3.0132694259039963,
      "vx": -0.9917778666340249,
      "vy": -0.12797133763019883
    },
    "152": {
      "x": 47.35,
      "y": 43.85,
      "speed": 1.0,
      "dir": -2.999695598985632,
      "vx": -0.9899494936611669,
      "vy": -0.14142135623730667
    },
    "153": {
      "x": 45.85,
      "y": 43.65,
      "speed": 1.0,
      "dir": -3.009041121293117,
      "vx": -0.9912279006826344,
      "vy": -0.13216372009101982
    },
    "154": {
      "x": 44.35,
      "y": 43.45,
      "speed": 1.0,
      "dir": -3.009041121293122,
      "vx": -0.991227900682635,
      "vy": -0.13216372009101518
    },
    "155": {
      "x": 42.85,
      "y": 43.25,
      "speed": 1.0,
      "dir": -3.009041121293117,
      "vx": -0.9912279006826344,
      "vy": -0.13216372009101982
    },
    "156": {
      "x": 41.3,
      "y": 43.1,
      "speed": 1.0,
      "dir": -3.0451188784072074,
      "vx": -0.9953500135553002,
      "vy": -0.09632419486018916
    },
    "157": {
      "x": 39.8,
      "y": 42.9,
      "speed": 1.0,
      "dir": -3.009041121293117,
      "vx": -0.9912279006826344,
      "vy": -0.13216372009101982
    },
    "158": {
      "x": 38.35,
      "y": 42.65,
      "speed": 1.0,
      "dir": -2.97085744211451,
      "vx": -0.985460115744348,
      "vy": -0.1699069165076467
    },
    "159": {
      "x": 36.95,
      "y": 42.35,
      "speed": 1.0,
      "dir": -2.9304993203670486,
      "vx": -0.9778024140774099,
      "vy": -0.20952908873087175
    },
    "160": {
      "x": 35.45,
      "y": 42.15,
      "speed": 1.0,
      "dir": -3.009041121293117,
      "vx": -0.9912279006826344,
      "vy": -0.13216372009101982
    },
    "161": {
      "x": 33.95,
      "y": 41.95,
      "speed": 1.0,
      "dir": -3.009041121293122,
      "vx": -0.991227900682635,
      "vy": -0.13216372009101518
    },
    "162": {
      "x": 32.45,
      "y": 41.75,
      "speed": 1.0,
      "dir": -3.009041121293117,
      "vx": -0.9912279006826344,
      "vy": -0.13216372009101982
    },
    "163": {
      "x": 30.950000000000003,
      "y": 41.55,
      "speed": 1.0,
      "dir": -3.009041121293117,
      "vx": -0.9912279006826344,
      "vy": -0.13216372009101982
    },
    "164": {
      "x": 29.5,
      "y": 41.3,
      "speed": 1.0,
      "dir": -2.970857442114511,
      "vx": -0.985460115744348,
      "vy": -0.1699069165076459
    },
    "165": {
      "x": 27.95,
      "y": 41.15,
      "speed": 1.0,
      "dir": -3.0451188784072074,
      "vx": -0.9953500135553002,
      "vy": -0.09632419486018938
    },
    "166": {
      "x": 26.55,
      "y": 40.95,
      "speed": 1.0,
      "dir": -2.999695598985632,
      "vx": -0.9899494936611669,
      "vy": -0.14142135623730667
    },
    "167": {
      "x": 25.1,
      "y": 40.8,
      "speed": 1.0,
      "dir": -3.038511045067089,
      "vx": -0.9946917938265508,
      "vy": -0.1028991510855092
    },
    "168": {
      "x": 23.55,
      "y": 40.55,
      "speed": 1.0,
      "dir": -2.981679530431574,
      "vx": -0.9872411207126471,
      "vy": -0.15923243882462043
    },
    "169": {
      "x": 22.05,
      "y": 40.25,
      "speed": 1.0,
      "dir": -2.9441970937399145,
      "vx": -0.9805806756909206,
      "vy": -0.19611613513818227
    },
    "170": {
      "x": 20.55,
      "y": 40.05,
      "speed": 1.0,
      "dir": -3.009041121293117,
      "vx": -0.9912279006826344,
      "vy": -0.13216372009101982
    },
    "171": {
      "x": 19.0,
      "y": 39.8,
      "speed": 1.0,
      "dir": -2.981679530431574,
      "vx": -0.9872411207126471,
      "vy": -0.15923243882462043
    },
    "172": {
      "x": 17.55,
      "y": 39.65,
      "speed": 1.0,
      "dir": -3.038511045067094,
      "vx": -0.9946917938265513,
      "vy": -0.10289915108550438
    },
    "173": {
      "x": 16.15,
      "y": 39.45,
      "speed": 1.0,
      "dir": -2.9996955989856326,
      "vx": -0.989949493661167,
      "vy": -0.14142135623730634
    },
    "174": {
      "x": 14.600000000000001,
      "y": 39.2,
      "speed": 1.0,
      "dir": -2.9816795304315735,
      "vx": -0.9872411207126471,
      "vy": -0.1592324388246208
    },
    "175": {
      "x": 14.2,
      "y": 39.2,
      "speed": 1.0,
      "dir": 3.141592653589793,
      "vx": -1.0,
      "vy": 0.0
    }
  },
  "rg_hit_timestep": 174,
  "rg_outcome": "green",
  "scene_dims": [
    100,
    62
  ],
  "interval": 0.1,
  "friction": 0.0,
  "elasticity": 1.0,
  "timestep": 0.02,
  "timesteps_per_frame": 6,
  "num_frames": 176,
  "fps": 20.0,
  "target": {
    "size": 4.0,
    "shape": 1
  },
  "red_sensor": {
    "x": 65.0,
    "y": 4.4,
    "width": 23.0,
    "height": 23.5
  },
  "green_sensor": {
    "x": 11.4,
    "y": 25.6,
    "width": 30.0,
    "height": 13.6
  },
  "num_barriers": 4,
  "num_occs": 0
}